{"schema_version": 2, "description": "pT-reco dependent reco-msd corrections derived on groomed (g),ungroomed (u) mass as well as with (jec) and without (nojec)applying the JEC on the jet mass.", "corrections": [{"name": "means_g_jec", "description": "Fit to polynomial of order 1\nFit status: The unconstrained solution is optimal.\nchi2 = 9.210395246793923e-05, P(dof=4) = 1.000", "version": 1, "inputs": [{"name": "pt", "type": "real"}], "output": {"name": "output", "type": "real"}, "data": {"nodetype": "formula", "expression": "1.1999918559631275+-0.00015921563654454934*x", "parser": "TFormula", "variables": ["pt"]}}, {"name": "means_g_nojec", "description": "Fit to polynomial of order 1\nFit status: The unconstrained solution is optimal.\nchi2 = 5.215516180141544e-05, P(dof=4) = 1.000", "version": 1, "inputs": [{"name": "pt", "type": "real"}], "output": {"name": "output", "type": "real"}, "data": {"nodetype": "formula", "expression": "1.0611782049675895+-0.00010911304513075198*x", "parser": "TFormula", "variables": ["pt"]}}, {"name": "response_g_jec", "description": "Fit to polynomial of order 1\nFit status: The unconstrained solution is optimal.\nchi2 = 1.83582500565391e-06, P(dof=4) = 1.000", "version": 1, "inputs": [{"name": "pt", "type": "real"}], "output": {"name": "output", "type": "real"}, "data": {"nodetype": "formula", "expression": "1.1166269232924406+-7.663513451975907e-05*x", "parser": "TFormula", "variables": ["pt"]}}, {"name": "response_g_nojec", "description": "Fit to polynomial of order 1\nFit status: The unconstrained solution is optimal.\nchi2 = 3.030999597761801e-06, P(dof=4) = 1.000", "version": 1, "inputs": [{"name": "pt", "type": "real"}], "output": {"name": "output", "type": "real"}, "data": {"nodetype": "formula", "expression": "0.9813559387709144+-2.4751308687387125e-05*x", "parser": "TFormula", "variables": ["pt"]}}, {"name": "means_u_jec", "description": "Fit to polynomial of order 1\nFit status: The unconstrained solution is optimal.\nchi2 = 2.599574391735443e-05, P(dof=4) = 1.000", "version": 1, "inputs": [{"name": "pt", "type": "real"}], "output": {"name": "output", "type": "real"}, "data": {"nodetype": "formula", "expression": "1.106097101559656+0.0001915454111244355*x", "parser": "TFormula", "variables": ["pt"]}}, {"name": "means_u_nojec", "description": "Fit to polynomial of order 1\nFit status: The unconstrained solution is optimal.\nchi2 = 1.9491793442797975e-05, P(dof=4) = 1.000", "version": 1, "inputs": [{"name": "pt", "type": "real"}], "output": {"name": "output", "type": "real"}, "data": {"nodetype": "formula", "expression": "0.9631391189679683+0.00022389590247199709*x", "parser": "TFormula", "variables": ["pt"]}}, {"name": "response_u_jec", "description": "Fit to polynomial of order 1\nFit status: The unconstrained solution is optimal.\nchi2 = 3.3058737812735e-05, P(dof=4) = 1.000", "version": 1, "inputs": [{"name": "pt", "type": "real"}], "output": {"name": "output", "type": "real"}, "data": {"nodetype": "formula", "expression": "1.025579782228426+0.0002188965172349328*x", "parser": "TFormula", "variables": ["pt"]}}, {"name": "response_u_nojec", "description": "Fit to polynomial of order 1\nFit status: The unconstrained solution is optimal.\nchi2 = 0.0001369664196259746, P(dof=4) = 1.000", "version": 1, "inputs": [{"name": "pt", "type": "real"}], "output": {"name": "output", "type": "real"}, "data": {"nodetype": "formula", "expression": "0.9062573332153847+0.00021289647120269342*x", "parser": "TFormula", "variables": ["pt"]}}]}